{
    "palette": {
        "common": {
            "black": "#fff",
            "white": "#000"
        },
        "background": {
            "paper": "#000",
            "default": "#000"
        },
        "primary": {
            "light": "#000",
            "main": "#000",
            "dark": "000",
            "contrastText": "#fff"
        },
        "secondary": {
            "light": "rgba(42, 46, 82, 0.1);",
            "main": "rgb(54, 58, 101)",
            "dark": "#0b0d1afa",
            "contrastText": "#fff"
        },
        "error": {
            "light": "#e57373",
            "main": "#f44336",
            "dark": "#d32f2f",
            "contrastText": "#fff"
        },
        "text": {
            "primary": "rgba(16, 14, 29, 0.8)",
            "secondary": "rgba(16, 14, 29, 0.17)",
            "disabled": "rgba(0, 0, 0, 0.38)",
            "hint": "rgba(0, 0, 0, 0.38)",
            "hover":"#85878a"
        },
        "icon": {
            "main": "rgba(42, 46, 82, 0.1);",
            "moreicon": "rgba(42, 46, 82, 0.1);",
            "model": "#ffffffa3",
            "icons": "rgba(255, 255, 255, 0.1)"
        }
    }
}